setup.py
iou_distributions/Binomialdistribution.py
iou_distributions/Gaussiandistribution.py
iou_distributions/Generaldistribution.py
iou_distributions/__init__.py
iou_distributions.egg-info/PKG-INFO
iou_distributions.egg-info/SOURCES.txt
iou_distributions.egg-info/dependency_links.txt
iou_distributions.egg-info/not-zip-safe
iou_distributions.egg-info/top_level.txt