Metadata-Version: 1.0
Name: iou-distributions
Version: 0.2
Summary: Binomial and Gaussian distributions
Home-page: UNKNOWN
Author: Ikenna Ugwuegbulam
Author-email: UNKNOWN
License: UNKNOWN
Platform: UNKNOWN
